_alex_chi2.pyd
alex_chi2-0.1.7.dist-info/DESCRIPTION.rst
alex_chi2-0.1.7.dist-info/METADATA
alex_chi2-0.1.7.dist-info/RECORD
alex_chi2-0.1.7.dist-info/WHEEL
alex_chi2-0.1.7.dist-info/metadata.json
alex_chi2-0.1.7.dist-info/top_level.txt
