Metadata-Version: 2.0
Name: alex-chi2
Version: 0.1.7
Summary: Sum Squared Error calculator in c
Home-page: https://nepenthe.me/alex_chi2
Author: Alexander Templeton
Author-email: blakmatr@gmail.com
License: UNKNOWN
Platform: UNKNOWN
